pgtestdbpy/__init__.py
pgtestdbpy/py.typed
pgtestdbpy-0.0.1.dist-info/LICENSE
pgtestdbpy-0.0.1.dist-info/METADATA
pgtestdbpy-0.0.1.dist-info/WHEEL
pgtestdbpy-0.0.1.dist-info/top_level.txt
pgtestdbpy-0.0.1.dist-info/RECORD
