Metadata-Version: 2.1
Name: pgtestdbpy
Version: 0.0.1
Summary: pgtestdb Python clone
Author-email: Oliver Russell <ojhrussell@gmail.com>
Maintainer-email: Oliver Russell <ojhrussell@gmail.com>
License: MIT License
Project-URL: homepage, https://github.com/leontrolski/pgtestdbpy
Project-URL: documentation, https://github.com/leontrolski/pgtestdbpy
Project-URL: repository, https://github.com/leontrolski/pgtestdbpy.git
Keywords: postgres,testing
Classifier: Programming Language :: Python
Requires-Python: >=3.7
License-File: LICENSE
Requires-Dist: psycopg >=3.1.0
Provides-Extra: dev
Requires-Dist: pytest >=7.0.0 ; extra == 'dev'
Requires-Dist: mypy >=1.6.0 ; extra == 'dev'
